baselines/__init__.py
baselines/anchors_wrapper.py
baselines/lime_wrapper.py
baselines/shap_wrapper.py
gpe/__init__.py
gpe/core.py
gpe/explanation.py
gpe/metrics.py
gpe/novel_methods.py
gpe/tree_utils.py
gpe/variants.py
gpe/visualization.py
gpe_framework-1.0.1.dist-info/LICENSE
gpe_framework-1.0.1.dist-info/METADATA
gpe_framework-1.0.1.dist-info/WHEEL
gpe_framework-1.0.1.dist-info/top_level.txt
gpe_framework-1.0.1.dist-info/RECORD
