Metadata-Version: 2.1
Name: gpe-framework
Version: 1.0.1
Summary: Greedy-Prune-Explain: Minimal local explanations for decision tree predictions
Home-page: https://github.com/vladdehtiarov/gpe-framework
Author: Vladyslav Dehtiarov
Author-email: vvdehtiarov@gmail.com
Project-URL: Homepage, https://github.com/vladdehtiarov/gpe-framework
Project-URL: Documentation, https://github.com/vladdehtiarov/gpe-framework#readme
Project-URL: Repository, https://github.com/vladdehtiarov/gpe-framework
Project-URL: Issues, https://github.com/vladdehtiarov/gpe-framework/issues
Classifier: Development Status :: 4 - Beta
Classifier: Intended Audience :: Science/Research
Classifier: Intended Audience :: Developers
Classifier: License :: OSI Approved :: MIT License
Classifier: Operating System :: OS Independent
Classifier: Programming Language :: Python :: 3
Classifier: Programming Language :: Python :: 3.8
Classifier: Programming Language :: Python :: 3.9
Classifier: Programming Language :: Python :: 3.10
Classifier: Programming Language :: Python :: 3.11
Classifier: Programming Language :: Python :: 3.12
Classifier: Topic :: Scientific/Engineering :: Artificial Intelligence
Requires-Python: >=3.8
License-File: LICENSE
Requires-Dist: numpy<2.0.0,>=1.20.0
Requires-Dist: pandas>=1.3.0
Requires-Dist: scikit-learn>=1.0.0
Requires-Dist: scipy>=1.7.0
Requires-Dist: matplotlib>=3.4.0
Provides-Extra: baselines
Requires-Dist: lime>=0.2.0; extra == "baselines"
Requires-Dist: anchor-exp>=0.0.2; extra == "baselines"
Provides-Extra: dev
Requires-Dist: pytest>=7.0.0; extra == "dev"
Requires-Dist: black>=22.0.0; extra == "dev"
